tessarinified/__init__.py
tessarinified/main.py
tessarinified-0.1.8.dist-info/METADATA
tessarinified-0.1.8.dist-info/WHEEL
tessarinified-0.1.8.dist-info/top_level.txt
tessarinified-0.1.8.dist-info/RECORD
