Metadata-Version: 2.1
Name: tessarinified
Version: 0.1.8
Summary: n-complex numbers (Tessarines) in Python
Author: corruptconverter, slycedf, goblinovermind, jerridium
License: MIT
Classifier: Development Status :: 3 - Alpha
Requires-Dist: numpy
